{
    "$schema": "http://cyclonedx.org/schema/bom-1.4.schema.json",
    "bomFormat": "CycloneDX",
    "specVersion": "1.4",
    "serialNumber": "urn:uuid:cec2ca71-c824-45cc-aff9-2dbd2e5a44f9",
    "version": 1,
    "metadata": {
        "timestamp": "2023-11-02T12:15:59-04:00",
        "component": {
            "bom-ref": "0a38595564d8e277",
            "type": "container",
            "name": "quay.io/stolostron/metrics-collector",
            "version": "2.9.0-fe233aa3392e00ad636a646a2a96373f9e7ccbdb"
        }
    }
}