{
    "$schema": "http://cyclonedx.org/schema/bom-1.4.schema.json",
    "bomFormat": "CycloneDX",
    "specVersion": "1.4",
    "serialNumber": "urn:uuid:3368c745-9587-4fc7-a179-c60546770631",
    "version": 1,
    "metadata": {
        "timestamp": "2023-11-02T12:21:16-04:00",
        "component": {
            "bom-ref": "38d46395038dd6a9",
            "type": "container",
            "name": "quay.io/stolostron/search-v2-api",
            "version": "2.9.0-2a7272b4ec14be855da6050b710d9679e6d11381"
        }
    }
}